LICENSE
MANIFEST.in
README.rst
setup.cfg
setup.py
./robo/__init__.py
./robo/_compat.py
./robo/decorators.py
./robo/message.py
./robo/robot.py
./robo/utils.py
./robo/adapters/__init__.py
./robo/adapters/shell.py
./robo/adapters/slack.py
./robo/handlers/__init__.py
./robo/handlers/echo.py
./robo/handlers/help.py
./robo/handlers/ping.py
./tests/fixtures/__init__.py
./tests/fixtures/bar.py
./tests/fixtures/foo.py
./tests/fixtures/adapters/__init__.py
./tests/fixtures/adapters/null.py
./tests/fixtures/handlers/__init__.py
./tests/fixtures/handlers/foo.py
robo/__init__.py
robo/_compat.py
robo/decorators.py
robo/message.py
robo/robot.py
robo/utils.py
robo.egg-info/PKG-INFO
robo.egg-info/SOURCES.txt
robo.egg-info/dependency_links.txt
robo.egg-info/requires.txt
robo.egg-info/top_level.txt
robo/adapters/__init__.py
robo/adapters/shell.py
robo/adapters/slack.py
robo/handlers/__init__.py
robo/handlers/echo.py
robo/handlers/help.py
robo/handlers/ping.py