Metadata-Version: 1.1
Name: robo
Version: 0.5.6
Summary: Dead simple bot framework.
Home-page: http://github.com/heavenshell/py-robo
Author: Shinya Ohyanagi
Author-email: sohyanagi@gmail.com
License: BSD
Platform: any
Classifier: Development Status :: 4 - Beta
Classifier: Environment :: Web Environment
Classifier: Intended Audience :: Developers
Classifier: License :: OSI Approved :: BSD License
Classifier: Operating System :: OS Independent
Classifier: Programming Language :: Python
Classifier: Topic :: Communications :: Chat
Classifier: Topic :: Communications :: Conferencing
